computemateai/README.md
computemateai/__init__.py
computemateai/computemate_mcp.py
computemateai/config.py
computemateai/main.py
computemateai/main_old.py
computemateai/mcp_configurations.py
computemateai/package_name.txt
computemateai/requirements.txt
computemateai/version.txt
computemateai/core/systems.py
computemateai/etextedit/README.md
computemateai/ui/info.py
computemateai/ui/prompts.py
computemateai/ui/selection_dialog.py
computemateai/ui/text_area.py
computemateai-0.1.70.dist-info/METADATA
computemateai-0.1.70.dist-info/WHEEL
computemateai-0.1.70.dist-info/entry_points.txt
computemateai-0.1.70.dist-info/top_level.txt
computemateai-0.1.70.dist-info/RECORD
