Metadata-Version: 2.4
Name: computemateai
Version: 0.1.70
Summary: ComputeMate AI - Power up your productivity
Home-page: https://toolmate.ai
Author: Eliran Wong
Author-email: support@toolmate.ai
License: GNU General Public License (GPL)
Project-URL: Source, https://github.com/eliranwong/computemate
Project-URL: Tracker, https://github.com/eliranwong/computemate/issues
Project-URL: Documentation, https://github.com/eliranwong/computemate/wiki
Project-URL: Funding, https://www.paypal.me/toolmate
Keywords: mcp agent toolmate ai anthropic azure chatgpt cohere deepseek genai github googleai groq llamacpp mistral ollama openai vertexai xai
Classifier: Development Status :: 5 - Production/Stable
Classifier: Intended Audience :: End Users/Desktop
Classifier: Topic :: Utilities
Classifier: Topic :: Scientific/Engineering :: Artificial Intelligence
Classifier: Topic :: Software Development :: Build Tools
Classifier: License :: OSI Approved :: GNU General Public License v3 or later (GPLv3+)
Classifier: Programming Language :: Python :: 3.10
Classifier: Programming Language :: Python :: 3.11
Classifier: Programming Language :: Python :: 3.12
Requires-Python: >=3.10, <3.13
Requires-Dist: agentmake>=1.1.10
Requires-Dist: agentmakemcp>=0.0.8
Requires-Dist: fastmcp[cli]
Requires-Dist: rich
Requires-Dist: alive-progress
Requires-Dist: click
Requires-Dist: tabulate
Provides-Extra: genai
Requires-Dist: google-genai>=1.42.0; extra == "genai"
Dynamic: author
Dynamic: author-email
Dynamic: classifier
Dynamic: description
Dynamic: home-page
Dynamic: keywords
Dynamic: license
Dynamic: project-url
Dynamic: provides-extra
Dynamic: requires-dist
Dynamic: requires-python
Dynamic: summary
